landuo/__init__.py
landuo/_lpnotusedict.py
landuo/_lpusedict.py
landuo/_states.py
landuo/cachedproperty.py
landuo/exceptions.py
landuo-1.0.0.dist-info/LICENSE
landuo-1.0.0.dist-info/METADATA
landuo-1.0.0.dist-info/WHEEL
landuo-1.0.0.dist-info/top_level.txt
landuo-1.0.0.dist-info/RECORD
