Metadata-Version: 2.1
Name: landuo
Version: 1.0.0
Summary: cachedproperty = property + cached_property
Author-email: Jim Chng <jimchng@outlook.com>
License: MIT License
Project-URL: Homepage, https://github.com/landuo-developers/landuo
Keywords: cachedproperty,lazy,property,cached,cached-property,cached_property
Classifier: License :: OSI Approved :: MIT License
Classifier: Programming Language :: Python
Classifier: Programming Language :: Python :: 3
Requires-Python: >=3.7
License-File: LICENSE
Provides-Extra: dev
